{
    "aa": "Afar",
    "ab": "Abkhazian",
    "ace": "Achinese",
    "ach": "Acoli",
    "ada": "Adangme",
    "ady": "Adyghe",
    "ae": "Avestan",
    "aeb": "Tunisian Arabic",
    "afh": "Afrihili",
    "ain": "Ainu",
    "akk": "Akkadian",
    "akz": "Alabama",
    "ale": "Aleut",
    "aln": "Gheg Albanian",
    "alt": "Southern Altai",
    "an": "Aragonese",
    "ang": "Old English",
    "anp": "Angika",
    "ar_001": "Modern Standard Arabic",
    "arc": "Aramaic",
    "arn": "Mapuche",
    "aro": "Araona",
    "arp": "Arapaho",
    "arq": "Algerian Arabic",
    "ars": "Najdi Arabic",
    "arw": "Arawak",
    "ary": "Moroccan Arabic",
    "arz": "Egyptian Arabic",
    "ase": "American Sign Language",
    "av": "Avaric",
    "avk": "Kotava",
    "awa": "Awadhi",
    "ay": "Aymara",
    "ba": "Bashkir",
    "bal": "Baluchi",
    "ban": "Balinese",
    "bar": "Bavarian",
    "bax": "Bamun",
    "bbc": "Batak Toba",
    "bbj": "Ghomala",
    "bej": "Beja",
    "bew": "Betawi",
    "bfd": "Bafut",
    "bfq": "Badaga",
    "bgn": "Western Balochi",
    "bho": "Bhojpuri",
    "bi": "Bislama",
    "bik": "Bikol",
    "bin": "Bini",
    "bjn": "Banjar",
    "bkm": "Kom",
    "bla": "Siksika",
    "bpy": "Bishnupriya",
    "bqi": "Bakhtiari",
    "bra": "Braj",
    "brh": "Brahui",
    "bss": "Akoose",
    "bua": "Buriat",
    "bug": "Buginese",
    "bum": "Bulu",
    "byn": "Blin",
    "byv": "Medumba",
    "cad": "Caddo",
    "car": "Carib",
    "cay": "Cayuga",
    "cch": "Atsam",
    "ceb": "Cebuano",
    "ch": "Chamorro",
    "chb": "Chibcha",
    "chg": "Chagatai",
    "chk": "Chuukese",
    "chm": "Mari",
    "chn": "Chinook Jargon",
    "cho": "Choctaw",
    "chp": "Chipewyan",
    "chy": "Cheyenne",
    "co": "Corsican",
    "cop": "Coptic",
    "cps": "Capiznon",
    "cr": "Cree",
    "crh": "Crimean Turkish",
    "crs": "Seselwa Creole French",
    "csb": "Kashubian",
    "cv": "Chuvash",
    "dak": "Dakota",
    "dar": "Dargwa",
    "de_AT": "Austrian German",
    "del": "Delaware",
    "den": "Slave",
    "dgr": "Dogrib",
    "din": "Dinka",
    "doi": "Dogri",
    "dtp": "Central Dusun",
    "dum": "Middle Dutch",
    "dv": "Divehi",
    "dyu": "Dyula",
    "dzg": "Dazaga",
    "efi": "Efik",
    "egl": "Emilian",
    "egy": "Ancient Egyptian",
    "eka": "Ekajuk",
    "elx": "Elamite",
    "en_AU": "Australian English",
    "en_CA": "Canadian English",
    "en_GB": "UK English",
    "en_US": "US English",
    "enm": "Middle English",
    "es_419": "Latin American Spanish",
    "es_ES": "European Spanish",
    "es_MX": "Mexican Spanish",
    "esu": "Central Yupik",
    "ext": "Extremaduran",
    "fan": "Fang",
    "fat": "Fanti",
    "fit": "Tornedalen Finnish",
    "fj": "Fijian",
    "fon": "Fon",
    "fr_CA": "Canadian French",
    "fr_CH": "Swiss French",
    "frc": "Cajun French",
    "frm": "Middle French",
    "fro": "Old French",
    "frp": "Arpitan",
    "frr": "Northern Frisian",
    "frs": "Eastern Frisian",
    "gaa": "Ga",
    "gag": "Gagauz",
    "gan": "Gan Chinese",
    "gay": "Gayo",
    "gba": "Gbaya",
    "gbz": "Zoroastrian Dari",
    "gez": "Geez",
    "gil": "Gilbertese",
    "glk": "Gilaki",
    "gmh": "Middle High German",
    "gn": "Guarani",
    "goh": "Old High German",
    "gom": "Goan Konkani",
    "gon": "Gondi",
    "gor": "Gorontalo",
    "got": "Gothic",
    "grb": "Grebo",
    "grc": "Ancient Greek",
    "guc": "Wayuu",
    "gur": "Frafra",
    "gwi": "Gwichʼin",
    "hai": "Haida",
    "hak": "Hakka Chinese",
    "hif": "Fiji Hindi",
    "hil": "Hiligaynon",
    "hit": "Hittite",
    "hmn": "Hmong",
    "ho": "Hiri Motu",
    "hsn": "Xiang Chinese",
    "ht": "Haitian Creole",
    "hup": "Hupa",
    "hz": "Herero",
    "ia": "Interlingua",
    "iba": "Iban",
    "ibb": "Ibibio",
    "ie": "Interlingue",
    "ik": "Inupiaq",
    "ilo": "Iloko",
    "inh": "Ingush",
    "io": "Ido",
    "iu": "Inuktitut",
    "izh": "Ingrian",
    "jam": "Jamaican Creole English",
    "jbo": "Lojban",
    "jpr": "Judeo-Persian",
    "jrb": "Judeo-Arabic",
    "jut": "Jutish",
    "jv": "Javanese",
    "kaa": "Kara-Kalpak",
    "kac": "Kachin",
    "kaj": "Jju",
    "kaw": "Kawi",
    "kbd": "Kabardian",
    "kbl": "Kanembu",
    "kcg": "Tyap",
    "ken": "Kenyang",
    "kfo": "Koro",
    "kg": "Kongo",
    "kgp": "Kaingang",
    "kha": "Khasi",
    "kho": "Khotanese",
    "khw": "Khowar",
    "kiu": "Kirmanjki",
    "kj": "Kuanyama",
    "kmb": "Kimbundu",
    "koi": "Komi-Permyak",
    "kos": "Kosraean",
    "kpe": "Kpelle",
    "kr": "Kanuri",
    "krc": "Karachay-Balkar",
    "kri": "Krio",
    "krj": "Kinaray-a",
    "krl": "Karelian",
    "kru": "Kurukh",
    "ku": "Kurdish",
    "kum": "Kumyk",
    "kut": "Kutenai",
    "kv": "Komi",
    "la": "Latin",
    "lad": "Ladino",
    "lah": "Lahnda",
    "lam": "Lamba",
    "lez": "Lezghian",
    "lfn": "Lingua Franca Nova",
    "li": "Limburgish",
    "lij": "Ligurian",
    "liv": "Livonian",
    "lmo": "Lombard",
    "lol": "Mongo",
    "loz": "Lozi",
    "ltg": "Latgalian",
    "lua": "Luba-Lulua",
    "lui": "Luiseno",
    "lun": "Lunda",
    "lus": "Mizo",
    "lzh": "Literary Chinese",
    "lzz": "Laz",
    "mad": "Madurese",
    "maf": "Mafa",
    "mag": "Magahi",
    "mai": "Maithili",
    "mak": "Makasar",
    "man": "Mandingo",
    "mde": "Maba",
    "mdf": "Moksha",
    "mdr": "Mandar",
    "men": "Mende",
    "mga": "Middle Irish",
    "mh": "Marshallese",
    "mi": "Maori",
    "mic": "Mi'kmaq",
    "min": "Minangkabau",
    "mnc": "Manchu",
    "mni": "Manipuri",
    "moh": "Mohawk",
    "mos": "Mossi",
    "mrj": "Western Mari",
    "mul": "Multiple languages",
    "mus": "Creek",
    "mwl": "Mirandese",
    "mwr": "Marwari",
    "mwv": "Mentawai",
    "mye": "Myene",
    "myv": "Erzya",
    "na": "Nauru",
    "nan": "Min Nan Chinese",
    "nap": "Neapolitan",
    "new": "Newari",
    "ng": "Ndonga",
    "nia": "Nias",
    "niu": "Niuean",
    "njo": "Ao Naga",
    "nl_BE": "Flemish",
    "no": "Norwegian",
    "nog": "Nogai",
    "non": "Old Norse",
    "nov": "Novial",
    "nqo": "N’Ko",
    "nr": "South Ndebele",
    "nso": "Northern Sotho",
    "nv": "Navajo",
    "nwc": "Classical Newari",
    "ny": "Nyanja",
    "nym": "Nyamwezi",
    "nyo": "Nyoro",
    "nzi": "Nzima",
    "oc": "Occitan",
    "oj": "Ojibwa",
    "osa": "Osage",
    "ota": "Ottoman Turkish",
    "pag": "Pangasinan",
    "pal": "Pahlavi",
    "pam": "Pampanga",
    "pap": "Papiamento",
    "pau": "Palauan",
    "pcd": "Picard",
    "pcm": "Nigerian Pidgin",
    "pdc": "Pennsylvania German",
    "pdt": "Plautdietsch",
    "peo": "Old Persian",
    "pfl": "Palatine German",
    "phn": "Phoenician",
    "pi": "Pali",
    "pms": "Piedmontese",
    "pnt": "Pontic",
    "pon": "Pohnpeian",
    "pro": "Old Provençal",
    "pt_BR": "Brazilian Portuguese",
    "quc": "Kʼicheʼ",
    "qug": "Chimborazo Highland Quichua",
    "raj": "Rajasthani",
    "rap": "Rapanui",
    "rar": "Rarotongan",
    "rgn": "Romagnol",
    "rif": "Riffian",
    "ro_MD": "Moldavian",
    "rom": "Romany",
    "rtm": "Rotuman",
    "rue": "Rusyn",
    "rug": "Roviana",
    "rup": "Aromanian",
    "sa": "Sanskrit",
    "sad": "Sandawe",
    "sam": "Samaritan Aramaic",
    "sas": "Sasak",
    "sat": "Santali",
    "saz": "Saurashtra",
    "sba": "Ngambay",
    "sc": "Sardinian",
    "scn": "Sicilian",
    "sco": "Scots",
    "sd": "Sindhi",
    "sdc": "Sassarese Sardinian",
    "sdh": "Southern Kurdish",
    "see": "Seneca",
    "sei": "Seri",
    "sel": "Selkup",
    "sga": "Old Irish",
    "sgs": "Samogitian",
    "sh": "Serbo-Croatian",
    "shn": "Shan",
    "shu": "Chadian Arabic",
    "sid": "Sidamo",
    "sli": "Lower Silesian",
    "sly": "Selayar",
    "sm": "Samoan",
    "sma": "Southern Sami",
    "smj": "Lule Sami",
    "sms": "Skolt Sami",
    "snk": "Soninke",
    "sog": "Sogdien",
    "srn": "Sranan Tongo",
    "srr": "Serer",
    "ss": "Swati",
    "ssy": "Saho",
    "st": "Southern Sotho",
    "stq": "Saterland Frisian",
    "su": "Sundanese",
    "suk": "Sukuma",
    "sus": "Susu",
    "sux": "Sumerian",
    "swb": "Comorian",
    "syc": "Classical Syriac",
    "syr": "Syriac",
    "szl": "Silesian",
    "tcy": "Tulu",
    "tem": "Timne",
    "ter": "Tereno",
    "tet": "Tetum",
    "tg": "Tajik",
    "tig": "Tigre",
    "tiv": "Tiv",
    "tkl": "Tokelau",
    "tkr": "Tsakhur",
    "tl": "Tagalog",
    "tlh": "Klingon",
    "tli": "Tlingit",
    "tly": "Talysh",
    "tmh": "Tamashek",
    "tn": "Tswana",
    "tog": "Nyasa Tonga",
    "tpi": "Tok Pisin",
    "tru": "Turoyo",
    "trv": "Taroko",
    "ts": "Tsonga",
    "tsd": "Tsakonian",
    "tsi": "Tsimshian",
    "tt": "Tatar",
    "ttt": "Muslim Tat",
    "tum": "Tumbuka",
    "tvl": "Tuvalu",
    "tw": "Twi",
    "ty": "Tahitian",
    "tyv": "Tuvinian",
    "udm": "Udmurt",
    "uga": "Ugaritic",
    "umb": "Umbundu",
    "und": "Unknown language",
    "ve": "Venda",
    "vec": "Venetian",
    "vep": "Veps",
    "vls": "West Flemish",
    "vmf": "Main-Franconian",
    "vot": "Votic",
    "vro": "Võro",
    "wa": "Walloon",
    "wal": "Wolaytta",
    "war": "Waray",
    "was": "Washo",
    "wbp": "Warlpiri",
    "wo": "Wolof",
    "wuu": "Wu Chinese",
    "xal": "Kalmyk",
    "xh": "Xhosa",
    "xmf": "Mingrelian",
    "yao": "Yao",
    "yap": "Yapese",
    "ybb": "Yemba",
    "yrl": "Nheengatu",
    "za": "Zhuang",
    "zap": "Zapotec",
    "zbl": "Blissymbols",
    "zea": "Zeelandic",
    "zen": "Zenaga",
    "zh_Hans": "Simplified Chinese",
    "zun": "Zuni",
    "zxx": "No linguistic content",
    "zza": "Zaza"
}